eosiopy/__init__.py
eosiopy/config.py
eosiopy/eosioapi.py
eosiopy/eosioparams.py
eosiopy/exception.py
eosiopy/log.py
eosiopy/nodenetwork.py
eosiopy/packedtransaction.py
eosiopy/rawinputparams.py
eosiopy/rmd160.so
eosiopy/sign.py
eosiopy/uECC.so
eosiopy/utils.py
eosiopy-0.0.6.dist-info/DESCRIPTION.rst
eosiopy-0.0.6.dist-info/METADATA
eosiopy-0.0.6.dist-info/RECORD
eosiopy-0.0.6.dist-info/WHEEL
eosiopy-0.0.6.dist-info/metadata.json
eosiopy-0.0.6.dist-info/top_level.txt
