Metadata-Version: 2.0
Name: eosiopy
Version: 0.0.6
Summary: Python library of the EOS.IO project.
Home-page: https://github.com/eosmoto/eosiopy
Author: eosmoto
Author-email: eosmoto@163.com
License: GPL-3.0
Keywords: eos,eosio,eosiopy,eospython,pythoneos,python eos,eos python
Platform: UNKNOWN
Classifier: Development Status :: 2 - Pre-Alpha
Classifier: License :: OSI Approved :: GNU General Public License v3 (GPLv3)
Classifier: Programming Language :: Python :: 3 :: Only
Classifier: Operating System :: POSIX
Classifier: Operating System :: MacOS
Requires-Dist: requests
Requires-Dist: base58
